majormode/__init__.py
majormode/heobs/__init__.py
majormode/heobs/client/__init__.py
majormode/heobs/client/service/__init__.py
majormode/heobs/client/service/alert_service.py
majormode/heobs/client/service/benefactor_service.py
majormode/heobs/client/service/expert_service.py
majormode/heobs/client/service/har_service.py
majormode/heobs/client/service/heobs_service.py
majormode/heobs/client/service/photo_service.py
majormode/heobs/client/service/watermark_service.py
heobs_restful_api_client_library-1.0.0.dist-info/METADATA
heobs_restful_api_client_library-1.0.0.dist-info/WHEEL
heobs_restful_api_client_library-1.0.0.dist-info/top_level.txt
heobs_restful_api_client_library-1.0.0.dist-info/RECORD
