Metadata-Version: 2.1
Name: heobs-restful-api-client-library
Version: 1.0.0
Summary: Heritage Observatory RESTful API Client Python Library
Home-page: UNKNOWN
Author: Daniel CAUNE
Author-email: daniel.caune@majormode.com
License: Copyright (C) 2019, Majormode
Platform: any
Classifier: License :: OSI Approved :: GNU General Public License (GPL)
Classifier: Development Status :: 5 - Production/Stable
Classifier: Topic :: Software Development :: Libraries :: Python Modules
Classifier: Programming Language :: Python
Requires-Python: >=3
Requires-Dist: pipfile
Requires-Dist: setuptools
Requires-Dist: wheel
Requires-Dist: twine
Requires-Dist: perseus-restful-api-client-library
